pygrpc/__init__.py
pygrpc/client.py
pygrpc/server.py
pygrpc/interceptors/__init__.py
pygrpc/interceptors/server/__init__.py
pygrpc/interceptors/server/logger.py
pygrpc/interceptors/server/recover.py
grpc_extensions-0.0.4.dist-info/METADATA
grpc_extensions-0.0.4.dist-info/WHEEL
grpc_extensions-0.0.4.dist-info/top_level.txt
grpc_extensions-0.0.4.dist-info/RECORD
