Metadata-Version: 2.1
Name: grpc-extensions
Version: 0.0.4
Summary: Python Grpc Library
Home-page: https://github.com/go-zs/python-grpc
Author: haoyinqianzui
Author-email: 810909753@qq.com
License: MIT Licence
Platform: any
Requires-Python: >=3.7.9
Requires-Dist: grpcio (>=1.32.0)
Requires-Dist: protobuf (>=3.14.0)
Requires-Dist: grpcio-opentracing (>=1.1.4)
Requires-Dist: grpc-interceptor (>=0.13.0)
